json_compare/__init__.py
json_compare/comparator.py
json_compare/log_processor.py
json_files_compare-1.0.1.dist-info/LICENSE
json_files_compare-1.0.1.dist-info/WHEEL
json_files_compare-1.0.1.dist-info/METADATA
json_files_compare-1.0.1.dist-info/RECORD
