Metadata-Version: 2.1
Name: json-files-compare
Version: 1.0.1
Summary: Simple but powerfull JSON-files comparator
Author: Alexey Novikov
Author-email: lexutka@gmail.com
Requires-Python: >=3.10,<4.0
Classifier: Programming Language :: Python :: 3
Classifier: Programming Language :: Python :: 3.10
